App.py
__init__.py
_version.py
one/__init__.py
one/one.py
two/__init__.py
two/two.py
LeroykTest-0.1.dev2.dist-info/LICENSE
LeroykTest-0.1.dev2.dist-info/METADATA
LeroykTest-0.1.dev2.dist-info/WHEEL
LeroykTest-0.1.dev2.dist-info/entry_points.txt
LeroykTest-0.1.dev2.dist-info/top_level.txt
LeroykTest-0.1.dev2.dist-info/RECORD
