Metadata-Version: 2.1
Name: LeroykTest
Version: 0.1.dev2
Summary: 用来测试python打包
Author: LeroyK
Author-email: bridieiybnf@gmail.com
License: MIT License
Project-URL: Project-URL, https://github.com/LeroyK111/python_packing_notes
Keywords: name,authors,urls
Classifier: Programming Language :: Python :: 3
Classifier: Development Status :: 4 - Beta
Requires-Python: >=3.6
License-File: LICENSE
Requires-Dist: requests
Requires-Dist: importlib-metadata ; python_version > "3.6"
Provides-Extra: pdf
Requires-Dist: ReportLab (>=1.2) ; extra == 'pdf'
Requires-Dist: RXP ; extra == 'pdf'
Provides-Extra: rest
Requires-Dist: docutils (>=0.3) ; extra == 'rest'
Requires-Dist: pack (==1.1,==1.3) ; extra == 'rest'
